workflowforge/__init__.py
workflowforge/ai_documentation.py
workflowforge/azure_devops.py
workflowforge/codebuild.py
workflowforge/environment.py
workflowforge/github_actions_module.py
workflowforge/jenkins.py
workflowforge/jenkins_plugins.py
workflowforge/job.py
workflowforge/schema_validation.py
workflowforge/secrets.py
workflowforge/step.py
workflowforge/strategy.py
workflowforge/templates.py
workflowforge/triggers.py
workflowforge/validation.py
workflowforge/visualization.py
workflowforge/workflow.py
workflowforge-1.1.3.dist-info/licenses/AUTHORS.md
workflowforge-1.1.3.dist-info/licenses/LICENSE
workflowforge-1.1.3.dist-info/METADATA
workflowforge-1.1.3.dist-info/WHEEL
workflowforge-1.1.3.dist-info/top_level.txt
workflowforge-1.1.3.dist-info/RECORD
