Metadata-Version: 2.4
Name: workflowforge
Version: 1.1.3
Summary: A robust and flexible library for creating GitHub Actions workflows, Jenkins pipelines, and AWS CodeBuild BuildSpecs programmatically in Python
Author-email: "Brainy Nimbus, LLC" <info@brainynimbus.io>
License: MIT
Project-URL: Homepage, https://brainynimbus.io/workflowforge
Project-URL: Repository, https://github.com/brainynimbus/workflowforge
Project-URL: Documentation, https://workflowforge.brainynimbus.io
Project-URL: Issues, https://github.com/brainynimbus/workflowforge/issues
Keywords: github-actions,jenkins,codebuild,aws,workflow,ci-cd,automation,yaml,devops,pipeline,buildspec
Classifier: Development Status :: 5 - Production/Stable
Classifier: Intended Audience :: Developers
Classifier: Programming Language :: Python :: 3
Classifier: Programming Language :: Python :: 3.11
Classifier: Programming Language :: Python :: 3.12
Classifier: Programming Language :: Python :: 3.13
Classifier: Topic :: Software Development :: Libraries :: Python Modules
Classifier: Topic :: Software Development :: Build Tools
Requires-Python: >=3.11
License-File: LICENSE
License-File: AUTHORS.md
Requires-Dist: ruamel.yaml>=0.18.0
Requires-Dist: pydantic>=2.0.0
Requires-Dist: typing-extensions>=4.0.0
Requires-Dist: requests>=2.25.0
Provides-Extra: dev
Requires-Dist: pytest>=7.0.0; extra == "dev"
Requires-Dist: pytest-cov>=4.0.0; extra == "dev"
Requires-Dist: black>=23.0.0; extra == "dev"
Requires-Dist: isort>=5.12.0; extra == "dev"
Requires-Dist: mypy>=1.0.0; extra == "dev"
Requires-Dist: pre-commit>=3.0.0; extra == "dev"
Requires-Dist: flake8>=7.0.0; extra == "dev"
Dynamic: license-file
